fman/__init__.py
fman/classx.py
fman/dataset.py
fman-0.0.1.dist-info/LICENSE
fman-0.0.1.dist-info/METADATA
fman-0.0.1.dist-info/WHEEL
fman-0.0.1.dist-info/top_level.txt
fman-0.0.1.dist-info/RECORD
