Metadata-Version: 2.1
Name: fman
Version: 0.0.1
Summary: FMan - A external module for builtin works tool for Python 3 (open source).
Home-page: https://github.com/almas-ali/fman
Author: Md. Almas Ali
Author-email: almaspr3@gmail.com
License: MIT
Platform: UNKNOWN
Classifier: Development Status :: 3 - Alpha
Classifier: Operating System :: OS Independent
Classifier: Intended Audience :: Developers
Classifier: License :: OSI Approved :: MIT License
Classifier: Programming Language :: Python :: 3
License-File: LICENSE
